Metadata-Version: 1.2
Name: jfind
Version: 0.0.1
Summary: A simple JSON search script.
Home-page: https://github.com/erickduran/jfind
Author: Erick Durán
Author-email: me@erickduran.com
License: GPL-3
Keywords: json search script
Platform: UNKNOWN
Classifier: Development Status :: 3 - Alpha
Classifier: Topic :: Utilities
Classifier: License :: OSI Approved :: GNU General Public License v3 (GPLv3)
Requires-Python: >=3.5
